nanots.cpython-312-x86_64-linux-musl.so
nanots.libs/libstdc++-a9383cce.so.6.0.28
nanots.libs/libgcc_s-a04fdf82.so.1
nanots-0.26.0.dist-info/WHEEL
nanots-0.26.0.dist-info/top_level.txt
nanots-0.26.0.dist-info/METADATA
nanots-0.26.0.dist-info/RECORD
nanots-0.26.0.dist-info/licenses/LICENSE
